datacite_websnap-1.0.3.dist-info/METADATA
datacite_websnap-1.0.3.dist-info/WHEEL
datacite_websnap-1.0.3.dist-info/entry_points.txt
datacite_websnap-1.0.3.dist-info/licenses/LICENSE
datacite_websnap/__init__.py
datacite_websnap/cli.py
datacite_websnap/config.py
datacite_websnap/datacite_handler.py
datacite_websnap/exporter.py
datacite_websnap/logger.py
datacite_websnap/validators.py
datacite_websnap-1.0.3.dist-info/RECORD
